LICENSE
MANIFEST.in
README.md
setup.cfg
setup.py
tempest_helper/__init__.py
tempest_helper/analyse_trajectories.py
tempest_helper/load_trajectories.py
tempest_helper/plot_trajectories.py
tempest_helper/save_trajectories.py
tempest_helper/trajectory_manipulations.py
tempest_helper.egg-info/PKG-INFO
tempest_helper.egg-info/SOURCES.txt
tempest_helper.egg-info/dependency_links.txt
tempest_helper.egg-info/requires.txt
tempest_helper.egg-info/top_level.txt