Metadata-Version: 2.1
Name: tempest-helper
Version: 0.1.0
Summary: tempest_helper is a Python module for the easier manipulation of TempestExtremes data.
Home-page: https://github.com/MetOffice/tempest_helper
Download-URL: https://github.com/MetOffice/tempest_helper/releases
Author: Met Office
Author-email: jon.seddon@metoffice.gov.uk
License: BSD 3-Clause License
Keywords: TempestExtremes,climate,tracking
Platform: UNKNOWN
Classifier: Development Status :: 5 - Production/Stable
Classifier: License :: OSI Approved :: BSD License
Classifier: Natural Language :: English
Classifier: Topic :: Scientific/Engineering :: Atmospheric Science
Classifier: Programming Language :: Python :: 3.7
Classifier: Programming Language :: Python :: 3.8
Classifier: Programming Language :: Python :: 3.9
Classifier: Programming Language :: Python :: 3.10
License-File: LICENSE
